[
  {
    "createdBy": "e1542d3e9a434bcfab474174e92b099f",
    "createdDate": 1615506716243,
    "id": "00b4e910835744c6b9facaf4b0150cd2",
    "internalTimestamp": "000001615506716243.000247803865414468",
    "lastModifiedDate": 1615506716243,
    "relType": "IsAbout",
    "sourceId": "c7ba76265a0043bdb0e1f701df6cd432",
    "targetId": "996feffe2ecb4b5e89aa0edca586d23c",
    "type": "CreativeWorkIsAboutDefinedTerm",
    "visibleToAuthenticatedUsers": false,
    "visibleToPublicUsers": false
  },
  {
    "createdBy": "e1542d3e9a434bcfab474174e92b099f",
    "createdDate": 1616968282562,
    "id": "f917fcb889774d649fc288e167350fd5",
    "internalTimestamp": "000001616968282562.000159324985553968",
    "lastModifiedDate": 1616968282562,
    "relType": "IsAbout",
    "sourceId": "40ea3d8aa1c6462aaea6e2c4ad1edc31",
    "targetId": "98e7c463262049b191d396b744e1e240",
    "type": "CreativeWorkIsAboutDefinedTerm",
    "visibleToAuthenticatedUsers": false,
    "visibleToPublicUsers": false
  },
  {
    "createdBy": "e1542d3e9a434bcfab474174e92b099f",
    "createdDate": 1616707493213,
    "id": "f3a8ab83d3f84fe4af320681db9566e0",
    "internalTimestamp": "000001616707493213.000102302025615222",
    "lastModifiedDate": 1616707493213,
    "relType": "IsAbout",
    "sourceId": "db91aa4a9ee7475cb381cdb0781d2820",
    "targetId": "5361c257315845e8b611a2598f718624",
    "type": "CreativeWorkIsAboutDefinedTerm",
    "visibleToAuthenticatedUsers": false,
    "visibleToPublicUsers": false
  },
  {
    "createdBy": "e1542d3e9a434bcfab474174e92b099f",
    "createdDate": 1616707493995,
    "id": "139f802f52424dd4ba8380c0ec54ebcb",
    "internalTimestamp": "000001616707493995.000102302807534598",
    "lastModifiedDate": 1616707493995,
    "relType": "IsAbout",
    "sourceId": "db91aa4a9ee7475cb381cdb0781d2820",
    "targetId": "60326372f2a44c79bcd6d0b984f8678d",
    "type": "CreativeWorkIsAboutDefinedTerm",
    "visibleToAuthenticatedUsers": false,
    "visibleToPublicUsers": false
  },
  {
    "createdBy": "e1542d3e9a434bcfab474174e92b099f",
    "createdDate": 1616534518511,
    "id": "b7e72ae853ae4047a9998e5e0b5bee3b",
    "internalTimestamp": "000001616534518512.000004529105462619",
    "lastModifiedDate": 1616534518511,
    "relType": "IsAbout",
    "sourceId": "f729f23be05047fdafa5adfe3ffbbeb0",
    "targetId": "5361c257315845e8b611a2598f718624",
    "type": "CreativeWorkIsAboutDefinedTerm",
    "visibleToAuthenticatedUsers": false,
    "visibleToPublicUsers": false
  },
  {
    "createdBy": "e1542d3e9a434bcfab474174e92b099f",
    "createdDate": 1616707408125,
    "id": "205cac76a11b451fbf05796ad4e58421",
    "internalTimestamp": "000001616707408125.000102216936211184",
    "lastModifiedDate": 1616707408125,
    "relType": "IsAbout",
    "sourceId": "91d69ebfc06141f6b1c969b982cc43a7",
    "targetId": "5361c257315845e8b611a2598f718624",
    "type": "CreativeWorkIsAboutDefinedTerm",
    "visibleToAuthenticatedUsers": false,
    "visibleToPublicUsers": false
  },
  {
    "createdBy": "e1542d3e9a434bcfab474174e92b099f",
    "createdDate": 1616707408768,
    "id": "a9248dd4b63a4f7a9969cc331c30f3f3",
    "internalTimestamp": "000001616707408768.000102217578994375",
    "lastModifiedDate": 1616707408768,
    "relType": "IsAbout",
    "sourceId": "91d69ebfc06141f6b1c969b982cc43a7",
    "targetId": "60326372f2a44c79bcd6d0b984f8678d",
    "type": "CreativeWorkIsAboutDefinedTerm",
    "visibleToAuthenticatedUsers": false,
    "visibleToPublicUsers": false
  },
  {
    "createdBy": "e1542d3e9a434bcfab474174e92b099f",
    "createdDate": 1617661017030,
    "id": "6f47584a033d472789d3d1fcbf2b80fc",
    "internalTimestamp": "000001617661017031.000221760122527843",
    "lastModifiedDate": 1617661017030,
    "relType": "IsAbout",
    "sourceId": "b63678a22bc148f8b797df801d76aa5b",
    "targetId": "98e7c463262049b191d396b744e1e240",
    "type": "CreativeWorkIsAboutDefinedTerm",
    "visibleToAuthenticatedUsers": false,
    "visibleToPublicUsers": false
  },
  {
    "createdBy": "e1542d3e9a434bcfab474174e92b099f",
    "createdDate": 1617661020739,
    "id": "bc95ad05f1a1481eaa260e4a3778dcbd",
    "internalTimestamp": "000001617661020739.000221763831198317",
    "lastModifiedDate": 1617661020739,
    "relType": "IsAbout",
    "sourceId": "b63678a22bc148f8b797df801d76aa5b",
    "targetId": "3ddacf037bcc4d5388683fb016d77d58",
    "type": "CreativeWorkIsAboutDefinedTerm",
    "visibleToAuthenticatedUsers": false,
    "visibleToPublicUsers": false
  },
  {
    "createdBy": "e1542d3e9a434bcfab474174e92b099f",
    "createdDate": 1617661026120,
    "id": "59b121f463214ba19cce5e86ecff95f9",
    "internalTimestamp": "000001617661026121.000221769212871864",
    "lastModifiedDate": 1617661026120,
    "relType": "IsAbout",
    "sourceId": "b63678a22bc148f8b797df801d76aa5b",
    "targetId": "0bf4a8fed2e1411491d77cbdfb59a542",
    "type": "CreativeWorkIsAboutDefinedTerm",
    "visibleToAuthenticatedUsers": false,
    "visibleToPublicUsers": false
  },
  {
    "createdBy": "e1542d3e9a434bcfab474174e92b099f",
    "createdDate": 1615841223169,
    "id": "b5714be0c1824a5bbdcc6d3e2eb9ba93",
    "internalTimestamp": "000001615841223169.000330044359072752",
    "lastModifiedDate": 1615841223169,
    "relType": "IsAbout",
    "sourceId": "2a2d18a3e4284f9fbcbb8a19c9808ba3",
    "targetId": "15236dbae9e244088c06a8ab2b519009",
    "type": "CreativeWorkIsAboutDefinedTerm",
    "visibleToAuthenticatedUsers": false,
    "visibleToPublicUsers": false
  },
  {
    "createdBy": "e1542d3e9a434bcfab474174e92b099f",
    "createdDate": 1615841228966,
    "id": "d67cf8bc4dc1416aa3fb699590d4ac80",
    "internalTimestamp": "000001615841228967.000330050156799562",
    "lastModifiedDate": 1615841228966,
    "relType": "IsAbout",
    "sourceId": "2a2d18a3e4284f9fbcbb8a19c9808ba3",
    "targetId": "30f16eac7bcd40a6a986a9df39a2e477",
    "type": "CreativeWorkIsAboutDefinedTerm",
    "visibleToAuthenticatedUsers": false,
    "visibleToPublicUsers": false
  },
  {
    "createdBy": "e1542d3e9a434bcfab474174e92b099f",
    "createdDate": 1615841236429,
    "id": "182b90be812b43aba0d6ac599a181371",
    "internalTimestamp": "000001615841236430.000330057620055880",
    "lastModifiedDate": 1615841236429,
    "relType": "IsAbout",
    "sourceId": "2a2d18a3e4284f9fbcbb8a19c9808ba3",
    "targetId": "1f3dd8564fe547e1a571d20484917756",
    "type": "CreativeWorkIsAboutDefinedTerm",
    "visibleToAuthenticatedUsers": false,
    "visibleToPublicUsers": false
  },
  {
    "createdBy": "e1542d3e9a434bcfab474174e92b099f",
    "createdDate": 1616969076953,
    "id": "8bcf944471f740b8958b23bc667342e7",
    "internalTimestamp": "000001616969076954.000160119478476304",
    "lastModifiedDate": 1616969076953,
    "relType": "IsAbout",
    "sourceId": "19645bf194704cc0badca1cb8312d532",
    "targetId": "3ddacf037bcc4d5388683fb016d77d58",
    "type": "CreativeWorkIsAboutDefinedTerm",
    "visibleToAuthenticatedUsers": false,
    "visibleToPublicUsers": false
  },
  {
    "createdBy": "e1542d3e9a434bcfab474174e92b099f",
    "createdDate": 1617914522947,
    "id": "155f5323215943d7b1754166512e9913",
    "internalTimestamp": "000001617914522947.000084529359145127",
    "lastModifiedDate": 1617914522947,
    "relType": "IsAbout",
    "sourceId": "45e054c7a05744f2b3cad2524a1f8c3e",
    "targetId": "a8907bdf4b42470d98cf1bc6cc0c17bc",
    "type": "CreativeWorkIsAboutDefinedTerm",
    "visibleToAuthenticatedUsers": false,
    "visibleToPublicUsers": false
  },
  {
    "createdBy": "e1542d3e9a434bcfab474174e92b099f",
    "createdDate": 1616705839011,
    "id": "ea281397edfe4173b44a86f40bd11fe8",
    "internalTimestamp": "000001616705839011.000100647792380143",
    "lastModifiedDate": 1616705839011,
    "relType": "IsAbout",
    "sourceId": "5bc2af370078482fbc336ac666459bc2",
    "targetId": "5361c257315845e8b611a2598f718624",
    "type": "CreativeWorkIsAboutDefinedTerm",
    "visibleToAuthenticatedUsers": false,
    "visibleToPublicUsers": false
  },
  {
    "createdBy": "e1542d3e9a434bcfab474174e92b099f",
    "createdDate": 1617660911309,
    "id": "6f01c95c4f834221b53816b24c2f3713",
    "internalTimestamp": "000001617660911310.000221654398379832",
    "lastModifiedDate": 1617660911309,
    "relType": "IsAbout",
    "sourceId": "153490971ddd409e8ef59cc16f47d99c",
    "targetId": "fbfe4fe864dc4aa9924d4be3effc8ee3",
    "type": "CreativeWorkIsAboutDefinedTerm",
    "visibleToAuthenticatedUsers": false,
    "visibleToPublicUsers": false
  },
  {
    "createdBy": "e1542d3e9a434bcfab474174e92b099f",
    "createdDate": 1616705609600,
    "id": "28a8a9d8ba1240e594a164d56a415a6d",
    "internalTimestamp": "000001616705609601.000100418377612937",
    "lastModifiedDate": 1616705609600,
    "relType": "IsAbout",
    "sourceId": "384fa6f2f2a545d79ab9746b4f24dc0a",
    "targetId": "5361c257315845e8b611a2598f718624",
    "type": "CreativeWorkIsAboutDefinedTerm",
    "visibleToAuthenticatedUsers": false,
    "visibleToPublicUsers": false
  },
  {
    "createdBy": "e1542d3e9a434bcfab474174e92b099f",
    "createdDate": 1617656948027,
    "id": "146a25caf0604fdd90b8891d1037c2d6",
    "internalTimestamp": "000001617656948027.000217691039059746",
    "lastModifiedDate": 1617656948027,
    "relType": "IsAbout",
    "sourceId": "f56cfdd351ec44a89d4dfc0837548ea7",
    "targetId": "5361c257315845e8b611a2598f718624",
    "type": "CreativeWorkIsAboutDefinedTerm",
    "visibleToAuthenticatedUsers": false,
    "visibleToPublicUsers": false
  },
  {
    "createdBy": "e1542d3e9a434bcfab474174e92b099f",
    "createdDate": 1617917542982,
    "id": "62edb6a4d6104392a64b3eaf7b2d1fcb",
    "internalTimestamp": "000001617917542983.000087549503303208",
    "lastModifiedDate": 1617917542982,
    "relType": "IsAbout",
    "sourceId": "737800c1b7b94cdb90814b44555cf2f4",
    "targetId": "15236dbae9e244088c06a8ab2b519009",
    "type": "CreativeWorkIsAboutDefinedTerm",
    "visibleToAuthenticatedUsers": false,
    "visibleToPublicUsers": false
  },
  {
    "createdBy": "e1542d3e9a434bcfab474174e92b099f",
    "createdDate": 1617917554624,
    "id": "4db72f1c1c2440bd9a47834a094e9e25",
    "internalTimestamp": "000001617917554624.000087561145414599",
    "lastModifiedDate": 1617917554624,
    "relType": "IsAbout",
    "sourceId": "737800c1b7b94cdb90814b44555cf2f4",
    "targetId": "996feffe2ecb4b5e89aa0edca586d23c",
    "type": "CreativeWorkIsAboutDefinedTerm",
    "visibleToAuthenticatedUsers": false,
    "visibleToPublicUsers": false
  },
  {
    "createdBy": "e1542d3e9a434bcfab474174e92b099f",
    "createdDate": 1617914664459,
    "id": "0b4260738b544d48b1093fe9d2c02cef",
    "internalTimestamp": "000001617914664460.000084670876523051",
    "lastModifiedDate": 1617914664459,
    "relType": "IsAbout",
    "sourceId": "7d2d82110af046f7b2c304423842899e",
    "targetId": "08d4f58cbec246daacff6b2569decc93",
    "type": "CreativeWorkIsAboutDefinedTerm",
    "visibleToAuthenticatedUsers": false,
    "visibleToPublicUsers": false
  },
  {
    "createdBy": "e1542d3e9a434bcfab474174e92b099f",
    "createdDate": 1615842153306,
    "id": "b5a0824ae7114469be75ddbaff9c693d",
    "internalTimestamp": "000001615842153306.000330974544265545",
    "lastModifiedDate": 1615842153306,
    "relType": "IsAbout",
    "sourceId": "ee605eda55234ac38c5f9e42e1666477",
    "targetId": "15236dbae9e244088c06a8ab2b519009",
    "type": "CreativeWorkIsAboutDefinedTerm",
    "visibleToAuthenticatedUsers": false,
    "visibleToPublicUsers": false
  },
  {
    "createdBy": "e1542d3e9a434bcfab474174e92b099f",
    "createdDate": 1615842213615,
    "id": "3279b7901b5a46c79340a6c3a331d647",
    "internalTimestamp": "000001615842213615.000331034855464512",
    "lastModifiedDate": 1615842213615,
    "relType": "IsAbout",
    "sourceId": "ee605eda55234ac38c5f9e42e1666477",
    "targetId": "c69778656d8d495d9fb657fe425e810a",
    "type": "CreativeWorkIsAboutDefinedTerm",
    "visibleToAuthenticatedUsers": false,
    "visibleToPublicUsers": false
  },
  {
    "createdBy": "e1542d3e9a434bcfab474174e92b099f",
    "createdDate": 1615842217891,
    "id": "e094a0eecab949ae9fc65df9055fc686",
    "internalTimestamp": "000001615842217892.000331039132037841",
    "lastModifiedDate": 1615842217891,
    "relType": "IsAbout",
    "sourceId": "ee605eda55234ac38c5f9e42e1666477",
    "targetId": "fbfe4fe864dc4aa9924d4be3effc8ee3",
    "type": "CreativeWorkIsAboutDefinedTerm",
    "visibleToAuthenticatedUsers": false,
    "visibleToPublicUsers": false
  },
  {
    "createdBy": "e1542d3e9a434bcfab474174e92b099f",
    "createdDate": 1615842240212,
    "id": "79e88a6dc8f24b3bbda43fa37d0c506e",
    "internalTimestamp": "000001615842240213.000331061453827215",
    "lastModifiedDate": 1615842240212,
    "relType": "IsAbout",
    "sourceId": "ee605eda55234ac38c5f9e42e1666477",
    "targetId": "5ac511fe3912471aae3d05b186a2ad91",
    "type": "CreativeWorkIsAboutDefinedTerm",
    "visibleToAuthenticatedUsers": false,
    "visibleToPublicUsers": false
  },
  {
    "createdBy": "e1542d3e9a434bcfab474174e92b099f",
    "createdDate": 1616968430470,
    "id": "6304ac71576f466e92310b5eeacf5dfd",
    "internalTimestamp": "000001616968430470.000159472891629891",
    "lastModifiedDate": 1616968430470,
    "relType": "IsAbout",
    "sourceId": "62e497490f6b4c3ead94ae0b5dad133c",
    "targetId": "0bf4a8fed2e1411491d77cbdfb59a542",
    "type": "CreativeWorkIsAboutDefinedTerm",
    "visibleToAuthenticatedUsers": false,
    "visibleToPublicUsers": false
  },
  {
    "createdBy": "e1542d3e9a434bcfab474174e92b099f",
    "createdDate": 1616968434397,
    "id": "c124208930e34afc8d61915e757b0f03",
    "internalTimestamp": "000001616968434397.000159476818143258",
    "lastModifiedDate": 1616968434397,
    "relType": "IsAbout",
    "sourceId": "62e497490f6b4c3ead94ae0b5dad133c",
    "targetId": "98e7c463262049b191d396b744e1e240",
    "type": "CreativeWorkIsAboutDefinedTerm",
    "visibleToAuthenticatedUsers": false,
    "visibleToPublicUsers": false
  },
  {
    "createdBy": "e1542d3e9a434bcfab474174e92b099f",
    "createdDate": 1616968438089,
    "id": "736e06853a7b4956b02b7536a4fbccee",
    "internalTimestamp": "000001616968438089.000159480510248603",
    "lastModifiedDate": 1616968438089,
    "relType": "IsAbout",
    "sourceId": "62e497490f6b4c3ead94ae0b5dad133c",
    "targetId": "5361c257315845e8b611a2598f718624",
    "type": "CreativeWorkIsAboutDefinedTerm",
    "visibleToAuthenticatedUsers": false,
    "visibleToPublicUsers": false
  },
  {
    "createdBy": "e1542d3e9a434bcfab474174e92b099f",
    "createdDate": 1616968472469,
    "id": "cd86fe4f01d14fee990c7a49b781feaa",
    "internalTimestamp": "000001616968472470.000159514890338360",
    "lastModifiedDate": 1616968472469,
    "relType": "IsAbout",
    "sourceId": "62e497490f6b4c3ead94ae0b5dad133c",
    "targetId": "30f16eac7bcd40a6a986a9df39a2e477",
    "type": "CreativeWorkIsAboutDefinedTerm",
    "visibleToAuthenticatedUsers": false,
    "visibleToPublicUsers": false
  },
  {
    "createdBy": "e1542d3e9a434bcfab474174e92b099f",
    "createdDate": 1616968479438,
    "id": "199e01171af348ba8d4a966fdc255709",
    "internalTimestamp": "000001616968479439.000159521859244702",
    "lastModifiedDate": 1616968479438,
    "relType": "IsAbout",
    "sourceId": "62e497490f6b4c3ead94ae0b5dad133c",
    "targetId": "1f3dd8564fe547e1a571d20484917756",
    "type": "CreativeWorkIsAboutDefinedTerm",
    "visibleToAuthenticatedUsers": false,
    "visibleToPublicUsers": false
  },
  {
    "createdBy": "e1542d3e9a434bcfab474174e92b099f",
    "createdDate": 1615581364473,
    "id": "468f9a5f48ee4becbb7094ff8c9928d1",
    "internalTimestamp": "000001615581364473.000278060909668993",
    "lastModifiedDate": 1615581364473,
    "relType": "IsAbout",
    "sourceId": "9b8a94a1ef9a481fae73728858d48207",
    "targetId": "c69778656d8d495d9fb657fe425e810a",
    "type": "CreativeWorkIsAboutDefinedTerm",
    "visibleToAuthenticatedUsers": false,
    "visibleToPublicUsers": false
  },
  {
    "createdBy": "e1542d3e9a434bcfab474174e92b099f",
    "createdDate": 1615581468704,
    "id": "81fa2c68450841899e95f48fb1fcb1f4",
    "internalTimestamp": "000001615581468704.000278165141055182",
    "lastModifiedDate": 1615581468704,
    "relType": "IsAbout",
    "sourceId": "9b8a94a1ef9a481fae73728858d48207",
    "targetId": "0b316c1160a347758fdc05b3c094b6be",
    "type": "CreativeWorkIsAboutDefinedTerm",
    "visibleToAuthenticatedUsers": false,
    "visibleToPublicUsers": false
  },
  {
    "createdBy": "e1542d3e9a434bcfab474174e92b099f",
    "createdDate": 1615584386459,
    "id": "a9886244c36545fab1dd5b7b3fc153cf",
    "internalTimestamp": "000001615584386459.000281082990097164",
    "lastModifiedDate": 1615584386459,
    "relType": "IsAbout",
    "sourceId": "9b8a94a1ef9a481fae73728858d48207",
    "targetId": "5ac511fe3912471aae3d05b186a2ad91",
    "type": "CreativeWorkIsAboutDefinedTerm",
    "visibleToAuthenticatedUsers": false,
    "visibleToPublicUsers": false
  },
  {
    "createdBy": "e1542d3e9a434bcfab474174e92b099f",
    "createdDate": 1617658008081,
    "id": "b4f3cfa20bbf4fb3a11b8982ccb27472",
    "internalTimestamp": "000001617658008081.000218751082833414",
    "lastModifiedDate": 1617658008081,
    "relType": "IsAbout",
    "sourceId": "75a8d3115d884443b72aff9987153c8a",
    "targetId": "5361c257315845e8b611a2598f718624",
    "type": "CreativeWorkIsAboutDefinedTerm",
    "visibleToAuthenticatedUsers": false,
    "visibleToPublicUsers": false
  },
  {
    "createdBy": "e1542d3e9a434bcfab474174e92b099f",
    "createdDate": 1617658009238,
    "id": "02d4e6f2a4af405da4c963d4353697ed",
    "internalTimestamp": "000001617658009239.000218752239918804",
    "lastModifiedDate": 1617658009238,
    "relType": "IsAbout",
    "sourceId": "75a8d3115d884443b72aff9987153c8a",
    "targetId": "60326372f2a44c79bcd6d0b984f8678d",
    "type": "CreativeWorkIsAboutDefinedTerm",
    "visibleToAuthenticatedUsers": false,
    "visibleToPublicUsers": false
  },
  {
    "createdBy": "e1542d3e9a434bcfab474174e92b099f",
    "createdDate": 1617658018224,
    "id": "5651a887a1b34c0faa625b6bbaf3c8d9",
    "internalTimestamp": "000001617658018225.000218761226006901",
    "lastModifiedDate": 1617658018224,
    "relType": "IsAbout",
    "sourceId": "75a8d3115d884443b72aff9987153c8a",
    "targetId": "15236dbae9e244088c06a8ab2b519009",
    "type": "CreativeWorkIsAboutDefinedTerm",
    "visibleToAuthenticatedUsers": false,
    "visibleToPublicUsers": false
  },
  {
    "createdBy": "e1542d3e9a434bcfab474174e92b099f",
    "createdDate": 1617658098826,
    "id": "add2278c6a25478b9564c3b3a5e9a49e",
    "internalTimestamp": "000001617658098826.000218841829289993",
    "lastModifiedDate": 1617658098826,
    "relType": "IsAbout",
    "sourceId": "633381061fd94b5e9c1be61bf1563730",
    "targetId": "5361c257315845e8b611a2598f718624",
    "type": "CreativeWorkIsAboutDefinedTerm",
    "visibleToAuthenticatedUsers": false,
    "visibleToPublicUsers": false
  },
  {
    "createdBy": "e1542d3e9a434bcfab474174e92b099f",
    "createdDate": 1617658105431,
    "id": "a46bcec56138453bb6bf1aab4d875113",
    "internalTimestamp": "000001617658105431.000218848434517227",
    "lastModifiedDate": 1617658105431,
    "relType": "IsAbout",
    "sourceId": "633381061fd94b5e9c1be61bf1563730",
    "targetId": "3ddacf037bcc4d5388683fb016d77d58",
    "type": "CreativeWorkIsAboutDefinedTerm",
    "visibleToAuthenticatedUsers": false,
    "visibleToPublicUsers": false
  },
  {
    "createdBy": "e1542d3e9a434bcfab474174e92b099f",
    "createdDate": 1617915629365,
    "id": "db4f30d233e24d288a6b0216b0321fca",
    "internalTimestamp": "000001617915629365.000085635816795969",
    "lastModifiedDate": 1617915629365,
    "relType": "IsAbout",
    "sourceId": "7dcbf4c4032343139730c1f5db5c195c",
    "targetId": "c69778656d8d495d9fb657fe425e810a",
    "type": "CreativeWorkIsAboutDefinedTerm",
    "visibleToAuthenticatedUsers": false,
    "visibleToPublicUsers": false
  },
  {
    "createdBy": "e1542d3e9a434bcfab474174e92b099f",
    "createdDate": 1616969174037,
    "id": "a35eeb136bed4e81afe0fb960cd9c87a",
    "internalTimestamp": "000001616969174037.000160216564114165",
    "lastModifiedDate": 1616969174037,
    "relType": "IsAbout",
    "sourceId": "a69472c795f0431b9d9bb65b682a6011",
    "targetId": "3ddacf037bcc4d5388683fb016d77d58",
    "type": "CreativeWorkIsAboutDefinedTerm",
    "visibleToAuthenticatedUsers": false,
    "visibleToPublicUsers": false
  },
  {
    "createdBy": "e1542d3e9a434bcfab474174e92b099f",
    "createdDate": 1616707343179,
    "id": "85aa7f5820dc4d498496a0a29217ff7c",
    "internalTimestamp": "000001616707343179.000102151988905067",
    "lastModifiedDate": 1616707343179,
    "relType": "IsAbout",
    "sourceId": "96eafc5ee4f946ada0f159a8aa7a7872",
    "targetId": "5361c257315845e8b611a2598f718624",
    "type": "CreativeWorkIsAboutDefinedTerm",
    "visibleToAuthenticatedUsers": false,
    "visibleToPublicUsers": false
  },
  {
    "createdBy": "e1542d3e9a434bcfab474174e92b099f",
    "createdDate": 1616707344499,
    "id": "614e6a77ad5945fba7dceca015b55534",
    "internalTimestamp": "000001616707344499.000102153309166106",
    "lastModifiedDate": 1616707344499,
    "relType": "IsAbout",
    "sourceId": "96eafc5ee4f946ada0f159a8aa7a7872",
    "targetId": "60326372f2a44c79bcd6d0b984f8678d",
    "type": "CreativeWorkIsAboutDefinedTerm",
    "visibleToAuthenticatedUsers": false,
    "visibleToPublicUsers": false
  },
  {
    "createdBy": "e1542d3e9a434bcfab474174e92b099f",
    "createdDate": 1617656783780,
    "id": "366b5bcbb8274267bb46efd28bdba2f4",
    "internalTimestamp": "000001617656783781.000217526786816023",
    "lastModifiedDate": 1617656783780,
    "relType": "IsAbout",
    "sourceId": "766b11910fac405fb239f9aae459090b",
    "targetId": "1f3dd8564fe547e1a571d20484917756",
    "type": "CreativeWorkIsAboutDefinedTerm",
    "visibleToAuthenticatedUsers": false,
    "visibleToPublicUsers": false
  },
  {
    "createdBy": "e1542d3e9a434bcfab474174e92b099f",
    "createdDate": 1617657174034,
    "id": "730d598775e4429d83ab9d4f36e277af",
    "internalTimestamp": "000001617657174034.000217917054327280",
    "lastModifiedDate": 1617657174034,
    "relType": "IsAbout",
    "sourceId": "766b11910fac405fb239f9aae459090b",
    "targetId": "98d4afe161864065a4ba77b80ab5bf31",
    "type": "CreativeWorkIsAboutDefinedTerm",
    "visibleToAuthenticatedUsers": false,
    "visibleToPublicUsers": false
  },
  {
    "createdBy": "e1542d3e9a434bcfab474174e92b099f",
    "createdDate": 1615581163102,
    "id": "0836f2fcf9c047b398b2b2abdd8534ab",
    "internalTimestamp": "000001615581163102.000277859537874050",
    "lastModifiedDate": 1615581163102,
    "relType": "IsAbout",
    "sourceId": "1fed265bf9444db3945fc096681577bd",
    "targetId": "0a6f5b2e78c94382b0c07287be8e9807",
    "type": "CreativeWorkIsAboutDefinedTerm",
    "visibleToAuthenticatedUsers": false,
    "visibleToPublicUsers": false
  },
  {
    "createdBy": "e1542d3e9a434bcfab474174e92b099f",
    "createdDate": 1615581164690,
    "id": "a774f0d42b0342e7bb3b0515455eef62",
    "internalTimestamp": "000001615581164690.000277861126237930",
    "lastModifiedDate": 1615581164690,
    "relType": "IsAbout",
    "sourceId": "1fed265bf9444db3945fc096681577bd",
    "targetId": "15236dbae9e244088c06a8ab2b519009",
    "type": "CreativeWorkIsAboutDefinedTerm",
    "visibleToAuthenticatedUsers": false,
    "visibleToPublicUsers": false
  },
  {
    "createdBy": "e1542d3e9a434bcfab474174e92b099f",
    "createdDate": 1615581189540,
    "id": "1a31a9b929284c6397a9b104d7182f8a",
    "internalTimestamp": "000001615581189540.000277885976162477",
    "lastModifiedDate": 1615581189540,
    "relType": "IsAbout",
    "sourceId": "1fed265bf9444db3945fc096681577bd",
    "targetId": "fbfe4fe864dc4aa9924d4be3effc8ee3",
    "type": "CreativeWorkIsAboutDefinedTerm",
    "visibleToAuthenticatedUsers": false,
    "visibleToPublicUsers": false
  },
  {
    "createdBy": "e1542d3e9a434bcfab474174e92b099f",
    "createdDate": 1615584893553,
    "id": "a33febdc2476464f9cd2f3973d1d6e37",
    "internalTimestamp": "000001615584893553.000281590149518640",
    "lastModifiedDate": 1615584893553,
    "relType": "IsAbout",
    "sourceId": "1fed265bf9444db3945fc096681577bd",
    "targetId": "5361c257315845e8b611a2598f718624",
    "type": "CreativeWorkIsAboutDefinedTerm",
    "visibleToAuthenticatedUsers": false,
    "visibleToPublicUsers": false
  },
  {
    "createdBy": "e1542d3e9a434bcfab474174e92b099f",
    "createdDate": 1617661112393,
    "id": "3ef04a1c9b654317b8391348d8cb038f",
    "internalTimestamp": "000001617661112393.000221855487413871",
    "lastModifiedDate": 1617661112393,
    "relType": "IsAbout",
    "sourceId": "f095d9f3d6be4c6380d4c35fa87aa1ce",
    "targetId": "60326372f2a44c79bcd6d0b984f8678d",
    "type": "CreativeWorkIsAboutDefinedTerm",
    "visibleToAuthenticatedUsers": false,
    "visibleToPublicUsers": false
  },
  {
    "createdBy": "e1542d3e9a434bcfab474174e92b099f",
    "createdDate": 1617661114471,
    "id": "21af841147af478e8a6dde3957062adc",
    "internalTimestamp": "000001617661114472.000221857566280669",
    "lastModifiedDate": 1617661114471,
    "relType": "IsAbout",
    "sourceId": "f095d9f3d6be4c6380d4c35fa87aa1ce",
    "targetId": "5361c257315845e8b611a2598f718624",
    "type": "CreativeWorkIsAboutDefinedTerm",
    "visibleToAuthenticatedUsers": false,
    "visibleToPublicUsers": false
  },
  {
    "createdBy": "e1542d3e9a434bcfab474174e92b099f",
    "createdDate": 1615543830233,
    "id": "065d56eea9c143f9a2877442f0c96771",
    "internalTimestamp": "000001615543830233.000257870763676896",
    "lastModifiedDate": 1615543830233,
    "relType": "IsAbout",
    "sourceId": "cec269b46d7e4784b0840d979d05f67e",
    "targetId": "29adc5a801cd41528b166f81da748aa4",
    "type": "CreativeWorkIsAboutDefinedTerm",
    "visibleToAuthenticatedUsers": false,
    "visibleToPublicUsers": false
  },
  {
    "createdBy": "e1542d3e9a434bcfab474174e92b099f",
    "createdDate": 1615584338940,
    "id": "640b2b888344489bbc95129d3e458c21",
    "internalTimestamp": "000001615584338940.000281035470022557",
    "lastModifiedDate": 1615584338940,
    "relType": "IsAbout",
    "sourceId": "cec269b46d7e4784b0840d979d05f67e",
    "targetId": "5361c257315845e8b611a2598f718624",
    "type": "CreativeWorkIsAboutDefinedTerm",
    "visibleToAuthenticatedUsers": false,
    "visibleToPublicUsers": false
  },
  {
    "createdBy": "e1542d3e9a434bcfab474174e92b099f",
    "createdDate": 1616165766293,
    "id": "3211c7344f6a48feb991269c52ddc2df",
    "internalTimestamp": "000001616165766293.000080475266077133",
    "lastModifiedDate": 1616165766293,
    "relType": "IsAbout",
    "sourceId": "8ce80525a8f54b37acd88ec728c5cceb",
    "targetId": "5361c257315845e8b611a2598f718624",
    "type": "CreativeWorkIsAboutDefinedTerm",
    "visibleToAuthenticatedUsers": false,
    "visibleToPublicUsers": false
  },
  {
    "createdBy": "e1542d3e9a434bcfab474174e92b099f",
    "createdDate": 1616165771605,
    "id": "915e996182e0405799379f49ca1e1f74",
    "internalTimestamp": "000001616165771605.000080480578426974",
    "lastModifiedDate": 1616165771605,
    "relType": "IsAbout",
    "sourceId": "8ce80525a8f54b37acd88ec728c5cceb",
    "targetId": "7943962392844375b96b436900c6dca6",
    "type": "CreativeWorkIsAboutDefinedTerm",
    "visibleToAuthenticatedUsers": false,
    "visibleToPublicUsers": false
  },
  {
    "createdBy": "e1542d3e9a434bcfab474174e92b099f",
    "createdDate": 1616165821346,
    "id": "2826bdf7fb7a4ccda282ce4a70b9b6d2",
    "internalTimestamp": "000001616165821347.000080530321225500",
    "lastModifiedDate": 1616165821346,
    "relType": "IsAbout",
    "sourceId": "8ce80525a8f54b37acd88ec728c5cceb",
    "targetId": "8dd492eb5eb241f49cc4f076669fbeaa",
    "type": "CreativeWorkIsAboutDefinedTerm",
    "visibleToAuthenticatedUsers": false,
    "visibleToPublicUsers": false
  },
  {
    "createdBy": "e1542d3e9a434bcfab474174e92b099f",
    "createdDate": 1616165827771,
    "id": "2314d69f5f75465daa13ca32104b4efc",
    "internalTimestamp": "000001616165827771.000080536745646936",
    "lastModifiedDate": 1616165827771,
    "relType": "IsAbout",
    "sourceId": "8ce80525a8f54b37acd88ec728c5cceb",
    "targetId": "63b49dd7dade406883744613da54d252",
    "type": "CreativeWorkIsAboutDefinedTerm",
    "visibleToAuthenticatedUsers": false,
    "visibleToPublicUsers": false
  },
  {
    "createdBy": "e1542d3e9a434bcfab474174e92b099f",
    "createdDate": 1616166880085,
    "id": "839f629c9eba4091894579ca7ebcbeb5",
    "internalTimestamp": "000001616166880085.000081589092589997",
    "lastModifiedDate": 1616166880085,
    "relType": "IsAbout",
    "sourceId": "8ce80525a8f54b37acd88ec728c5cceb",
    "targetId": "3ddacf037bcc4d5388683fb016d77d58",
    "type": "CreativeWorkIsAboutDefinedTerm",
    "visibleToAuthenticatedUsers": false,
    "visibleToPublicUsers": false
  },
  {
    "createdBy": "e1542d3e9a434bcfab474174e92b099f",
    "createdDate": 1616166924855,
    "id": "4be63369892141889c40a22febbceac0",
    "internalTimestamp": "000001616166924855.000081633863808958",
    "lastModifiedDate": 1616166924855,
    "relType": "IsAbout",
    "sourceId": "8ce80525a8f54b37acd88ec728c5cceb",
    "targetId": "98e7c463262049b191d396b744e1e240",
    "type": "CreativeWorkIsAboutDefinedTerm",
    "visibleToAuthenticatedUsers": false,
    "visibleToPublicUsers": false
  },
  {
    "createdBy": "e1542d3e9a434bcfab474174e92b099f",
    "createdDate": 1616600469117,
    "id": "9476fd8b0abe495dbd81400997e15a52",
    "internalTimestamp": "000001616600469117.000040330501158343",
    "lastModifiedDate": 1616600469117,
    "relType": "IsAbout",
    "sourceId": "a0e7bc885d124842815ea30d01345421",
    "targetId": "fbfe4fe864dc4aa9924d4be3effc8ee3",
    "type": "CreativeWorkIsAboutDefinedTerm",
    "visibleToAuthenticatedUsers": false,
    "visibleToPublicUsers": false
  },
  {
    "createdBy": "e1542d3e9a434bcfab474174e92b099f",
    "createdDate": 1616600442916,
    "id": "42f807d91c864fd0abcad18dd91b83e3",
    "internalTimestamp": "000001616600442916.000040304291534685",
    "lastModifiedDate": 1616600442916,
    "relType": "IsAbout",
    "sourceId": "4136c4ecc6a94b89a0b9ae4ae844a419",
    "targetId": "29adc5a801cd41528b166f81da748aa4",
    "type": "CreativeWorkIsAboutDefinedTerm",
    "visibleToAuthenticatedUsers": false,
    "visibleToPublicUsers": false
  },
  {
    "createdBy": "e1542d3e9a434bcfab474174e92b099f",
    "createdDate": 1616599951195,
    "id": "c829ab7e22be43ed8ab3abdf6c74cc9b",
    "internalTimestamp": "000001616599951195.000039812556789540",
    "lastModifiedDate": 1616599951195,
    "relType": "IsAbout",
    "sourceId": "f0a76d1c897046eea59bef0816700cf7",
    "targetId": "0a6f5b2e78c94382b0c07287be8e9807",
    "type": "CreativeWorkIsAboutDefinedTerm",
    "visibleToAuthenticatedUsers": false,
    "visibleToPublicUsers": false
  },
  {
    "createdBy": "e1542d3e9a434bcfab474174e92b099f",
    "createdDate": 1616600207391,
    "id": "5eac7aca466945daaa828f6b119680da",
    "internalTimestamp": "000001616600207392.000040068760419592",
    "lastModifiedDate": 1616600207391,
    "relType": "IsAbout",
    "sourceId": "ff7125d7324649d5af65df77acc5fefa",
    "targetId": "0a6f5b2e78c94382b0c07287be8e9807",
    "type": "CreativeWorkIsAboutDefinedTerm",
    "visibleToAuthenticatedUsers": false,
    "visibleToPublicUsers": false
  },
  {
    "createdBy": "e1542d3e9a434bcfab474174e92b099f",
    "createdDate": 1616600338975,
    "id": "bc851c28e2634720be09719d5a748524",
    "internalTimestamp": "000001616600338976.000040200348084269",
    "lastModifiedDate": 1616600338975,
    "relType": "IsAbout",
    "sourceId": "ef061adc2bff427ba014be78a4be4519",
    "targetId": "0a6f5b2e78c94382b0c07287be8e9807",
    "type": "CreativeWorkIsAboutDefinedTerm",
    "visibleToAuthenticatedUsers": false,
    "visibleToPublicUsers": false
  },
  {
    "createdBy": "e1542d3e9a434bcfab474174e92b099f",
    "createdDate": 1616600537601,
    "id": "efc8d096ffd64d00aa91cc0fa64fc370",
    "internalTimestamp": "000001616600537601.000040398997477220",
    "lastModifiedDate": 1616600537601,
    "relType": "IsAbout",
    "sourceId": "6b1afa0dccf243428db44baa94f97827",
    "targetId": "0bf4a8fed2e1411491d77cbdfb59a542",
    "type": "CreativeWorkIsAboutDefinedTerm",
    "visibleToAuthenticatedUsers": false,
    "visibleToPublicUsers": false
  },
  {
    "createdBy": "e1542d3e9a434bcfab474174e92b099f",
    "createdDate": 1616599931690,
    "id": "32ec5388016640e3a4425c6dc5dd6179",
    "internalTimestamp": "000001616599931690.000039793051157478",
    "lastModifiedDate": 1616599931690,
    "relType": "IsAbout",
    "sourceId": "f0a76d1c897046eea59bef0816700cf7",
    "targetId": "aee912ff04bf46bcb6762b13de514086",
    "type": "CreativeWorkIsAboutDefinedTerm",
    "visibleToAuthenticatedUsers": false,
    "visibleToPublicUsers": false
  },
  {
    "createdBy": "e1542d3e9a434bcfab474174e92b099f",
    "createdDate": 1616600315943,
    "id": "d7d988d496dc49d1a3e21d49f0b743a6",
    "internalTimestamp": "000001616600315943.000040177315273717",
    "lastModifiedDate": 1616600315943,
    "relType": "IsAbout",
    "sourceId": "45d9b67b097149a2a092c500162338ef",
    "targetId": "aee912ff04bf46bcb6762b13de514086",
    "type": "CreativeWorkIsAboutDefinedTerm",
    "visibleToAuthenticatedUsers": false,
    "visibleToPublicUsers": false
  },
  {
    "createdBy": "e1542d3e9a434bcfab474174e92b099f",
    "createdDate": 1616600399847,
    "id": "7b23b6b9270244d19b62fcb81bd5d2cd",
    "internalTimestamp": "000001616600399847.000040261221583539",
    "lastModifiedDate": 1616600399847,
    "relType": "IsAbout",
    "sourceId": "273f0f8e87054f1897e6d511d531449b",
    "targetId": "aee912ff04bf46bcb6762b13de514086",
    "type": "CreativeWorkIsAboutDefinedTerm",
    "visibleToAuthenticatedUsers": false,
    "visibleToPublicUsers": false
  },
  {
    "createdBy": "e1542d3e9a434bcfab474174e92b099f",
    "createdDate": 1616600421917,
    "id": "684a65ef78b84e479486fe057f6e2b4c",
    "internalTimestamp": "000001616600421917.000040283291881370",
    "lastModifiedDate": 1616600421917,
    "relType": "IsAbout",
    "sourceId": "0047a1777fc14ac2b9520930a545ca76",
    "targetId": "aee912ff04bf46bcb6762b13de514086",
    "type": "CreativeWorkIsAboutDefinedTerm",
    "visibleToAuthenticatedUsers": false,
    "visibleToPublicUsers": false
  },
  {
    "createdBy": "e1542d3e9a434bcfab474174e92b099f",
    "createdDate": 1616600437236,
    "id": "0e5574156bb94eb99c4269075cd14cc5",
    "internalTimestamp": "000001616600437236.000040298611239525",
    "lastModifiedDate": 1616600437236,
    "relType": "IsAbout",
    "sourceId": "4136c4ecc6a94b89a0b9ae4ae844a419",
    "targetId": "aee912ff04bf46bcb6762b13de514086",
    "type": "CreativeWorkIsAboutDefinedTerm",
    "visibleToAuthenticatedUsers": false,
    "visibleToPublicUsers": false
  },
  {
    "createdBy": "e1542d3e9a434bcfab474174e92b099f",
    "createdDate": 1616600358646,
    "id": "910f698fe54b45fc848ba60c984ae58e",
    "internalTimestamp": "000001616600358646.000040220018936298",
    "lastModifiedDate": 1616600358646,
    "relType": "IsAbout",
    "sourceId": "4103ace55794401f9faee9f3c9e1a55f",
    "targetId": "97826fe8d75a441bad7842cd758c01b0",
    "type": "CreativeWorkIsAboutDefinedTerm",
    "visibleToAuthenticatedUsers": false,
    "visibleToPublicUsers": false
  },
  {
    "createdBy": "e1542d3e9a434bcfab474174e92b099f",
    "createdDate": 1616600362494,
    "id": "320ce15eb5f440c1b067ac94cb56cfc9",
    "internalTimestamp": "000001616600362494.000040223867228273",
    "lastModifiedDate": 1616600362494,
    "relType": "IsAbout",
    "sourceId": "4103ace55794401f9faee9f3c9e1a55f",
    "targetId": "c69778656d8d495d9fb657fe425e810a",
    "type": "CreativeWorkIsAboutDefinedTerm",
    "visibleToAuthenticatedUsers": false,
    "visibleToPublicUsers": false
  },
  {
    "createdBy": "e1542d3e9a434bcfab474174e92b099f",
    "createdDate": 1616600297641,
    "id": "41935fe8501848a09e224e40d7557f20",
    "internalTimestamp": "000001616600297641.000040159012191394",
    "lastModifiedDate": 1616600297641,
    "relType": "IsAbout",
    "sourceId": "45d9b67b097149a2a092c500162338ef",
    "targetId": "15236dbae9e244088c06a8ab2b519009",
    "type": "CreativeWorkIsAboutDefinedTerm",
    "visibleToAuthenticatedUsers": false,
    "visibleToPublicUsers": false
  },
  {
    "createdBy": "e1542d3e9a434bcfab474174e92b099f",
    "createdDate": 1616600406342,
    "id": "a3f42cab066d476f9c9ea824b3126391",
    "internalTimestamp": "000001616600406343.000040267716878483",
    "lastModifiedDate": 1616600406342,
    "relType": "IsAbout",
    "sourceId": "273f0f8e87054f1897e6d511d531449b",
    "targetId": "63b49dd7dade406883744613da54d252",
    "type": "CreativeWorkIsAboutDefinedTerm",
    "visibleToAuthenticatedUsers": false,
    "visibleToPublicUsers": false
  },
  {
    "createdBy": "e1542d3e9a434bcfab474174e92b099f",
    "createdDate": 1616600416148,
    "id": "a21678173de54387b4f9f6a5a4f61300",
    "internalTimestamp": "000001616600416148.000040277522642448",
    "lastModifiedDate": 1616600416148,
    "relType": "IsAbout",
    "sourceId": "0047a1777fc14ac2b9520930a545ca76",
    "targetId": "63b49dd7dade406883744613da54d252",
    "type": "CreativeWorkIsAboutDefinedTerm",
    "visibleToAuthenticatedUsers": false,
    "visibleToPublicUsers": false
  },
  {
    "createdBy": "e1542d3e9a434bcfab474174e92b099f",
    "createdDate": 1616600556286,
    "id": "4f78488a55b84fb09d1b2c239bf4bbfe",
    "internalTimestamp": "000001616600556286.000040417683699987",
    "lastModifiedDate": 1616600556286,
    "relType": "IsAbout",
    "sourceId": "899e3bf51d154a0f98bbc4daae3278cb",
    "targetId": "98d4afe161864065a4ba77b80ab5bf31",
    "type": "CreativeWorkIsAboutDefinedTerm",
    "visibleToAuthenticatedUsers": false,
    "visibleToPublicUsers": false
  },
  {
    "createdBy": "e1542d3e9a434bcfab474174e92b099f",
    "createdDate": 1616022698114,
    "id": "42adc6a059054a4f8bab1ef979db473b",
    "internalTimestamp": "000001616022698115.000009060256911331",
    "lastModifiedDate": 1616022698114,
    "relType": "IsAbout",
    "sourceId": "f0a76d1c897046eea59bef0816700cf7",
    "targetId": "5361c257315845e8b611a2598f718624",
    "type": "CreativeWorkIsAboutDefinedTerm",
    "visibleToAuthenticatedUsers": false,
    "visibleToPublicUsers": false
  },
  {
    "createdBy": "e1542d3e9a434bcfab474174e92b099f",
    "createdDate": 1616600210970,
    "id": "8a064fb894944d2c905976e30caea17a",
    "internalTimestamp": "000001616600210971.000040072339406623",
    "lastModifiedDate": 1616600210970,
    "relType": "IsAbout",
    "sourceId": "ff7125d7324649d5af65df77acc5fefa",
    "targetId": "5361c257315845e8b611a2598f718624",
    "type": "CreativeWorkIsAboutDefinedTerm",
    "visibleToAuthenticatedUsers": false,
    "visibleToPublicUsers": false
  },
  {
    "createdBy": "e1542d3e9a434bcfab474174e92b099f",
    "createdDate": 1616600303447,
    "id": "8f9c16e203df47d484f530b91d3fad46",
    "internalTimestamp": "000001616600303448.000040164819067069",
    "lastModifiedDate": 1616600303447,
    "relType": "IsAbout",
    "sourceId": "45d9b67b097149a2a092c500162338ef",
    "targetId": "5361c257315845e8b611a2598f718624",
    "type": "CreativeWorkIsAboutDefinedTerm",
    "visibleToAuthenticatedUsers": false,
    "visibleToPublicUsers": false
  },
  {
    "createdBy": "e1542d3e9a434bcfab474174e92b099f",
    "createdDate": 1616600343535,
    "id": "8c7c99d2206e4277a6b2798e769c6440",
    "internalTimestamp": "000001616600343535.000040204907594699",
    "lastModifiedDate": 1616600343535,
    "relType": "IsAbout",
    "sourceId": "ef061adc2bff427ba014be78a4be4519",
    "targetId": "5361c257315845e8b611a2598f718624",
    "type": "CreativeWorkIsAboutDefinedTerm",
    "visibleToAuthenticatedUsers": false,
    "visibleToPublicUsers": false
  },
  {
    "createdBy": "e1542d3e9a434bcfab474174e92b099f",
    "createdDate": 1616600392412,
    "id": "af487d6eee7f4ef2a681a25309992c08",
    "internalTimestamp": "000001616600392412.000040253786104110",
    "lastModifiedDate": 1616600392412,
    "relType": "IsAbout",
    "sourceId": "273f0f8e87054f1897e6d511d531449b",
    "targetId": "5361c257315845e8b611a2598f718624",
    "type": "CreativeWorkIsAboutDefinedTerm",
    "visibleToAuthenticatedUsers": false,
    "visibleToPublicUsers": false
  },
  {
    "createdBy": "e1542d3e9a434bcfab474174e92b099f",
    "createdDate": 1616600414170,
    "id": "d22c9c6d2c8f4ba18e51f031a9118e42",
    "internalTimestamp": "000001616600414171.000040275545227233",
    "lastModifiedDate": 1616600414170,
    "relType": "IsAbout",
    "sourceId": "0047a1777fc14ac2b9520930a545ca76",
    "targetId": "5361c257315845e8b611a2598f718624",
    "type": "CreativeWorkIsAboutDefinedTerm",
    "visibleToAuthenticatedUsers": false,
    "visibleToPublicUsers": false
  },
  {
    "createdBy": "e1542d3e9a434bcfab474174e92b099f",
    "createdDate": 1616600432711,
    "id": "9b5dfef271144208a77a36145fb212e7",
    "internalTimestamp": "000001616600432711.000040294086272986",
    "lastModifiedDate": 1616600432711,
    "relType": "IsAbout",
    "sourceId": "4136c4ecc6a94b89a0b9ae4ae844a419",
    "targetId": "5361c257315845e8b611a2598f718624",
    "type": "CreativeWorkIsAboutDefinedTerm",
    "visibleToAuthenticatedUsers": false,
    "visibleToPublicUsers": false
  },
  {
    "createdBy": "e1542d3e9a434bcfab474174e92b099f",
    "createdDate": 1616600451865,
    "id": "d00e57df8ed044a2918613e52787affe",
    "internalTimestamp": "000001616600451865.000040313240767376",
    "lastModifiedDate": 1616600451865,
    "relType": "IsAbout",
    "sourceId": "a0e7bc885d124842815ea30d01345421",
    "targetId": "5361c257315845e8b611a2598f718624",
    "type": "CreativeWorkIsAboutDefinedTerm",
    "visibleToAuthenticatedUsers": false,
    "visibleToPublicUsers": false
  },
  {
    "createdBy": "e1542d3e9a434bcfab474174e92b099f",
    "createdDate": 1616600480348,
    "id": "8b9fb8ec295d4c1fa8299e7a30a68c80",
    "internalTimestamp": "000001616600480348.000040341737924587",
    "lastModifiedDate": 1616600480348,
    "relType": "IsAbout",
    "sourceId": "6b1afa0dccf243428db44baa94f97827",
    "targetId": "5361c257315845e8b611a2598f718624",
    "type": "CreativeWorkIsAboutDefinedTerm",
    "visibleToAuthenticatedUsers": false,
    "visibleToPublicUsers": false
  },
  {
    "createdBy": "e1542d3e9a434bcfab474174e92b099f",
    "createdDate": 1616601332630,
    "id": "774dade1b4f949b68f37eefba471792c",
    "internalTimestamp": "000001616601332630.000041194053838467",
    "lastModifiedDate": 1616601332630,
    "relType": "IsAbout",
    "sourceId": "899e3bf51d154a0f98bbc4daae3278cb",
    "targetId": "1f3dd8564fe547e1a571d20484917756",
    "type": "CreativeWorkIsAboutDefinedTerm",
    "visibleToAuthenticatedUsers": false,
    "visibleToPublicUsers": false
  },
  {
    "createdBy": "e1542d3e9a434bcfab474174e92b099f",
    "createdDate": 1616600489114,
    "id": "be38e1cb46f9460ca5a85e52d8f7cf2a",
    "internalTimestamp": "000001616600489114.000040350506137636",
    "lastModifiedDate": 1616600489114,
    "relType": "IsAbout",
    "sourceId": "6b1afa0dccf243428db44baa94f97827",
    "targetId": "98e7c463262049b191d396b744e1e240",
    "type": "CreativeWorkIsAboutDefinedTerm",
    "visibleToAuthenticatedUsers": false,
    "visibleToPublicUsers": false
  },
  {
    "createdBy": "e1542d3e9a434bcfab474174e92b099f",
    "createdDate": 1616600496481,
    "id": "8394066446ba4968bcc929c5594576e5",
    "internalTimestamp": "000001616600496481.000040357875160326",
    "lastModifiedDate": 1616600496481,
    "relType": "IsAbout",
    "sourceId": "6b1afa0dccf243428db44baa94f97827",
    "targetId": "3ddacf037bcc4d5388683fb016d77d58",
    "type": "CreativeWorkIsAboutDefinedTerm",
    "visibleToAuthenticatedUsers": false,
    "visibleToPublicUsers": false
  },
  {
    "createdBy": "e1542d3e9a434bcfab474174e92b099f",
    "createdDate": 1616600281928,
    "id": "26bd1d1784af4805b7b1f71c80b5bd1d",
    "internalTimestamp": "000001616600281928.000040143299137168",
    "lastModifiedDate": 1616600281928,
    "relType": "IsAbout",
    "sourceId": "f0a76d1c897046eea59bef0816700cf7",
    "targetId": "e74766464513438c8c7703493ca68731",
    "type": "CreativeWorkIsAboutDefinedTerm",
    "visibleToAuthenticatedUsers": false,
    "visibleToPublicUsers": false
  },
  {
    "createdBy": "e1542d3e9a434bcfab474174e92b099f",
    "createdDate": 1616600287744,
    "id": "1ed7be8d43b940ecaa3b32a4fd44dab5",
    "internalTimestamp": "000001616600287745.000040149115704106",
    "lastModifiedDate": 1616600287744,
    "relType": "IsAbout",
    "sourceId": "ff7125d7324649d5af65df77acc5fefa",
    "targetId": "e74766464513438c8c7703493ca68731",
    "type": "CreativeWorkIsAboutDefinedTerm",
    "visibleToAuthenticatedUsers": false,
    "visibleToPublicUsers": false
  },
  {
    "createdBy": "e1542d3e9a434bcfab474174e92b099f",
    "createdDate": 1616600336521,
    "id": "6c6774a1a7e6409e881ccb2466b58378",
    "internalTimestamp": "000001616600336521.000040197893388185",
    "lastModifiedDate": 1616600336521,
    "relType": "IsAbout",
    "sourceId": "ef061adc2bff427ba014be78a4be4519",
    "targetId": "e74766464513438c8c7703493ca68731",
    "type": "CreativeWorkIsAboutDefinedTerm",
    "visibleToAuthenticatedUsers": false,
    "visibleToPublicUsers": false
  },
  {
    "createdBy": "e1542d3e9a434bcfab474174e92b099f",
    "createdDate": 1616600385343,
    "id": "3c883f2fadb142db8ab24367c2a71302",
    "internalTimestamp": "000001616600385343.000040246716764292",
    "lastModifiedDate": 1616600385343,
    "relType": "IsAbout",
    "sourceId": "273f0f8e87054f1897e6d511d531449b",
    "targetId": "e74766464513438c8c7703493ca68731",
    "type": "CreativeWorkIsAboutDefinedTerm",
    "visibleToAuthenticatedUsers": false,
    "visibleToPublicUsers": false
  },
  {
    "createdBy": "e1542d3e9a434bcfab474174e92b099f",
    "createdDate": 1616600424131,
    "id": "96150e0bb44945988b7bb4875623447c",
    "internalTimestamp": "000001616600424132.000040285506521332",
    "lastModifiedDate": 1616600424131,
    "relType": "IsAbout",
    "sourceId": "0047a1777fc14ac2b9520930a545ca76",
    "targetId": "e74766464513438c8c7703493ca68731",
    "type": "CreativeWorkIsAboutDefinedTerm",
    "visibleToAuthenticatedUsers": false,
    "visibleToPublicUsers": false
  }
]