[
  {
    "createdBy": "e1542d3e9a434bcfab474174e92b099f",
    "createdDate": 1616019839271,
    "id": "f48571703a4246ac86a5cbbbe55026ee",
    "internalTimestamp": "000001616019839271.000006201329541203",
    "lastModifiedDate": 1616019839271,
    "relType": "has",
    "sourceId": "c7ba76265a0043bdb0e1f701df6cd432",
    "targetId": "4e3223d0019c489b90ffb050643e0602",
    "type": "CreativeWorkhasTypeLabel",
    "visibleToAuthenticatedUsers": false,
    "visibleToPublicUsers": false
  },
  {
    "createdBy": "e1542d3e9a434bcfab474174e92b099f",
    "createdDate": 1616019900842,
    "id": "88910ea276284ba298be1c0877de8b77",
    "internalTimestamp": "000001616019900842.000006262901892344",
    "lastModifiedDate": 1616019900842,
    "relType": "has",
    "sourceId": "1fed265bf9444db3945fc096681577bd",
    "targetId": "c9d142cad5ac4e56b6b43473afbddd65",
    "type": "CreativeWorkhasTypeLabel",
    "visibleToAuthenticatedUsers": false,
    "visibleToPublicUsers": false
  },
  {
    "createdBy": "e1542d3e9a434bcfab474174e92b099f",
    "createdDate": 1616019902549,
    "id": "4b8e5f2d6e0b46e9b4e0fb158031d149",
    "internalTimestamp": "000001616019902549.000006264609348661",
    "lastModifiedDate": 1616019902549,
    "relType": "has",
    "sourceId": "ee605eda55234ac38c5f9e42e1666477",
    "targetId": "c9d142cad5ac4e56b6b43473afbddd65",
    "type": "CreativeWorkhasTypeLabel",
    "visibleToAuthenticatedUsers": false,
    "visibleToPublicUsers": false
  },
  {
    "createdBy": "e1542d3e9a434bcfab474174e92b099f",
    "createdDate": 1616019903246,
    "id": "b085116ea47747f2a372c9ad12232008",
    "internalTimestamp": "000001616019903246.000006265306324084",
    "lastModifiedDate": 1616019903246,
    "relType": "has",
    "sourceId": "2a2d18a3e4284f9fbcbb8a19c9808ba3",
    "targetId": "c9d142cad5ac4e56b6b43473afbddd65",
    "type": "CreativeWorkhasTypeLabel",
    "visibleToAuthenticatedUsers": false,
    "visibleToPublicUsers": false
  },
  {
    "createdBy": "e1542d3e9a434bcfab474174e92b099f",
    "createdDate": 1616165854463,
    "id": "36d5e2a88bfe4c09868fa134d5d06ea7",
    "internalTimestamp": "000001616165854463.000080563438345390",
    "lastModifiedDate": 1616165854463,
    "relType": "has",
    "sourceId": "8ce80525a8f54b37acd88ec728c5cceb",
    "targetId": "c9d142cad5ac4e56b6b43473afbddd65",
    "type": "CreativeWorkhasTypeLabel",
    "visibleToAuthenticatedUsers": false,
    "visibleToPublicUsers": false
  },
  {
    "createdBy": "e1542d3e9a434bcfab474174e92b099f",
    "createdDate": 1616167315801,
    "id": "4e024ad0e27f47f496ac095f01fdd1ad",
    "internalTimestamp": "000001616167315801.000082024822225493",
    "lastModifiedDate": 1616167315801,
    "relType": "has",
    "sourceId": "f0a76d1c897046eea59bef0816700cf7",
    "targetId": "c9d142cad5ac4e56b6b43473afbddd65",
    "type": "QuotationhasTypeLabel",
    "visibleToAuthenticatedUsers": false,
    "visibleToPublicUsers": false
  },
  {
    "createdBy": "e1542d3e9a434bcfab474174e92b099f",
    "createdDate": 1616535487964,
    "id": "aedfb5e7c5c6459b8c00f4e060c8975a",
    "internalTimestamp": "000001616535487964.000005498586071493",
    "lastModifiedDate": 1616535487964,
    "relType": "has",
    "sourceId": "0c955856f2174dc4925fd04ee6048c83",
    "targetId": "c9d142cad5ac4e56b6b43473afbddd65",
    "type": "CreativeWorkhasTypeLabel",
    "visibleToAuthenticatedUsers": false,
    "visibleToPublicUsers": false
  },
  {
    "createdBy": "e1542d3e9a434bcfab474174e92b099f",
    "createdDate": 1616535929364,
    "id": "5bf75a2bbfc844a8a504ba8b63541d5d",
    "internalTimestamp": "000001616535929364.000005939998563542",
    "lastModifiedDate": 1616535929364,
    "relType": "has",
    "sourceId": "29445452fbed427e9cfda850c55acefa",
    "targetId": "c9d142cad5ac4e56b6b43473afbddd65",
    "type": "CreativeWorkhasTypeLabel",
    "visibleToAuthenticatedUsers": false,
    "visibleToPublicUsers": false
  },
  {
    "createdBy": "e1542d3e9a434bcfab474174e92b099f",
    "createdDate": 1616588679926,
    "id": "0e2e078a582e4da6b790fcb7c5e191e5",
    "internalTimestamp": "000001616588679926.000028541054262982",
    "lastModifiedDate": 1616588679926,
    "relType": "has",
    "sourceId": "ff7125d7324649d5af65df77acc5fefa",
    "targetId": "c9d142cad5ac4e56b6b43473afbddd65",
    "type": "CreativeWorkhasTypeLabel",
    "visibleToAuthenticatedUsers": false,
    "visibleToPublicUsers": false
  },
  {
    "createdBy": "e1542d3e9a434bcfab474174e92b099f",
    "createdDate": 1616588693772,
    "id": "343b5bca0fb94aacb6fd37cb4ccf22b6",
    "internalTimestamp": "000001616588693772.000028554901189024",
    "lastModifiedDate": 1616588693772,
    "relType": "has",
    "sourceId": "45d9b67b097149a2a092c500162338ef",
    "targetId": "c9d142cad5ac4e56b6b43473afbddd65",
    "type": "CreativeWorkhasTypeLabel",
    "visibleToAuthenticatedUsers": false,
    "visibleToPublicUsers": false
  },
  {
    "createdBy": "e1542d3e9a434bcfab474174e92b099f",
    "createdDate": 1616588737942,
    "id": "d1342de4c66947d3883d1fc3a97f2853",
    "internalTimestamp": "000001616588737942.000028599073674605",
    "lastModifiedDate": 1616588737942,
    "relType": "has",
    "sourceId": "ef061adc2bff427ba014be78a4be4519",
    "targetId": "c9d142cad5ac4e56b6b43473afbddd65",
    "type": "CreativeWorkhasTypeLabel",
    "visibleToAuthenticatedUsers": false,
    "visibleToPublicUsers": false
  },
  {
    "createdBy": "e1542d3e9a434bcfab474174e92b099f",
    "createdDate": 1616588747575,
    "id": "0c519b515f514782987019a9c66717ac",
    "internalTimestamp": "000001616588747575.000028608706814651",
    "lastModifiedDate": 1616588747575,
    "relType": "has",
    "sourceId": "273f0f8e87054f1897e6d511d531449b",
    "targetId": "c9d142cad5ac4e56b6b43473afbddd65",
    "type": "CreativeWorkhasTypeLabel",
    "visibleToAuthenticatedUsers": false,
    "visibleToPublicUsers": false
  },
  {
    "createdBy": "e1542d3e9a434bcfab474174e92b099f",
    "createdDate": 1616588753322,
    "id": "36c7c70d1ba442e08bf22186d2092f39",
    "internalTimestamp": "000001616588753322.000028614453995093",
    "lastModifiedDate": 1616588753322,
    "relType": "has",
    "sourceId": "0047a1777fc14ac2b9520930a545ca76",
    "targetId": "c9d142cad5ac4e56b6b43473afbddd65",
    "type": "CreativeWorkhasTypeLabel",
    "visibleToAuthenticatedUsers": false,
    "visibleToPublicUsers": false
  },
  {
    "createdBy": "e1542d3e9a434bcfab474174e92b099f",
    "createdDate": 1616588768988,
    "id": "6c14f8e7636445369136b22f4124083a",
    "internalTimestamp": "000001616588768988.000028630121010979",
    "lastModifiedDate": 1616588768988,
    "relType": "has",
    "sourceId": "6b1afa0dccf243428db44baa94f97827",
    "targetId": "c9d142cad5ac4e56b6b43473afbddd65",
    "type": "CreativeWorkhasTypeLabel",
    "visibleToAuthenticatedUsers": false,
    "visibleToPublicUsers": false
  },
  {
    "createdBy": "e1542d3e9a434bcfab474174e92b099f",
    "createdDate": 1616590498802,
    "id": "fd7f6db12e464c01a054551d5fed82a7",
    "internalTimestamp": "000001616590498802.000030359929402333",
    "lastModifiedDate": 1616590498802,
    "relType": "has",
    "sourceId": "899e3bf51d154a0f98bbc4daae3278cb",
    "targetId": "c9d142cad5ac4e56b6b43473afbddd65",
    "type": "CreativeWorkhasTypeLabel",
    "visibleToAuthenticatedUsers": false,
    "visibleToPublicUsers": false
  },
  {
    "createdBy": "e1542d3e9a434bcfab474174e92b099f",
    "createdDate": 1617656414197,
    "id": "54496906657f4288ac81edf48ee9cb47",
    "internalTimestamp": "000001617656414197.000217157189339999",
    "lastModifiedDate": 1617656414197,
    "relType": "has",
    "sourceId": "af4d2b2953974d528031aeac766941a4",
    "targetId": "c9d142cad5ac4e56b6b43473afbddd65",
    "type": "CreativeWorkhasTypeLabel",
    "visibleToAuthenticatedUsers": false,
    "visibleToPublicUsers": false
  },
  {
    "createdBy": "e1542d3e9a434bcfab474174e92b099f",
    "createdDate": 1617656794605,
    "id": "3f9b2d131d7649a49f7c6ee3014f0003",
    "internalTimestamp": "000001617656794605.000217537611520580",
    "lastModifiedDate": 1617656794605,
    "relType": "has",
    "sourceId": "766b11910fac405fb239f9aae459090b",
    "targetId": "c9d142cad5ac4e56b6b43473afbddd65",
    "type": "CreativeWorkhasTypeLabel",
    "visibleToAuthenticatedUsers": false,
    "visibleToPublicUsers": false
  },
  {
    "createdBy": "e1542d3e9a434bcfab474174e92b099f",
    "createdDate": 1617656956895,
    "id": "dc985ef2501e4eb09d8fd822e4b068e6",
    "internalTimestamp": "000001617656956895.000217699907617317",
    "lastModifiedDate": 1617656956895,
    "relType": "has",
    "sourceId": "f56cfdd351ec44a89d4dfc0837548ea7",
    "targetId": "c9d142cad5ac4e56b6b43473afbddd65",
    "type": "CreativeWorkhasTypeLabel",
    "visibleToAuthenticatedUsers": false,
    "visibleToPublicUsers": false
  },
  {
    "createdBy": "e1542d3e9a434bcfab474174e92b099f",
    "createdDate": 1617657635854,
    "id": "5bee70fbfd0b499fb677dc5768d773ab",
    "internalTimestamp": "000001617657635854.000218378891111459",
    "lastModifiedDate": 1617657635854,
    "relType": "has",
    "sourceId": "5e3f2fe7d1114bc98cf4258a2e21e8f2",
    "targetId": "c9d142cad5ac4e56b6b43473afbddd65",
    "type": "CreativeWorkhasTypeLabel",
    "visibleToAuthenticatedUsers": false,
    "visibleToPublicUsers": false
  },
  {
    "createdBy": "e1542d3e9a434bcfab474174e92b099f",
    "createdDate": 1617658024906,
    "id": "5d6e89419ca44a788c26ceaeb0f2f3e7",
    "internalTimestamp": "000001617658024906.000218767907655209",
    "lastModifiedDate": 1617658024906,
    "relType": "has",
    "sourceId": "75a8d3115d884443b72aff9987153c8a",
    "targetId": "c9d142cad5ac4e56b6b43473afbddd65",
    "type": "CreativeWorkhasTypeLabel",
    "visibleToAuthenticatedUsers": false,
    "visibleToPublicUsers": false
  },
  {
    "createdBy": "e1542d3e9a434bcfab474174e92b099f",
    "createdDate": 1617658114584,
    "id": "e94260e6aed24003923b2021f2ae2043",
    "internalTimestamp": "000001617658114584.000218857587690343",
    "lastModifiedDate": 1617658114584,
    "relType": "has",
    "sourceId": "633381061fd94b5e9c1be61bf1563730",
    "targetId": "c9d142cad5ac4e56b6b43473afbddd65",
    "type": "CreativeWorkhasTypeLabel",
    "visibleToAuthenticatedUsers": false,
    "visibleToPublicUsers": false
  },
  {
    "createdBy": "e1542d3e9a434bcfab474174e92b099f",
    "createdDate": 1617660960386,
    "id": "12f9e4f99efd41e59665083c73179225",
    "internalTimestamp": "000001617660960386.000221703475679802",
    "lastModifiedDate": 1617660960386,
    "relType": "has",
    "sourceId": "153490971ddd409e8ef59cc16f47d99c",
    "targetId": "c9d142cad5ac4e56b6b43473afbddd65",
    "type": "CreativeWorkhasTypeLabel",
    "visibleToAuthenticatedUsers": false,
    "visibleToPublicUsers": false
  },
  {
    "createdBy": "e1542d3e9a434bcfab474174e92b099f",
    "createdDate": 1617661034559,
    "id": "27c2c6a8979041a9a6d2649676cc661a",
    "internalTimestamp": "000001617661034559.000221777651646701",
    "lastModifiedDate": 1617661034559,
    "relType": "has",
    "sourceId": "b63678a22bc148f8b797df801d76aa5b",
    "targetId": "c9d142cad5ac4e56b6b43473afbddd65",
    "type": "CreativeWorkhasTypeLabel",
    "visibleToAuthenticatedUsers": false,
    "visibleToPublicUsers": false
  },
  {
    "createdBy": "e1542d3e9a434bcfab474174e92b099f",
    "createdDate": 1617661135332,
    "id": "9f100051f6fb4eb79c88a5f460a40c50",
    "internalTimestamp": "000001617661135332.000221878426985092",
    "lastModifiedDate": 1617661135332,
    "relType": "has",
    "sourceId": "f095d9f3d6be4c6380d4c35fa87aa1ce",
    "targetId": "c9d142cad5ac4e56b6b43473afbddd65",
    "type": "CreativeWorkhasTypeLabel",
    "visibleToAuthenticatedUsers": false,
    "visibleToPublicUsers": false
  },
  {
    "createdBy": "e1542d3e9a434bcfab474174e92b099f",
    "createdDate": 1617914378557,
    "id": "df1b94b5c2e842de9423959a29356c83",
    "internalTimestamp": "000001617914378558.000084384964245757",
    "lastModifiedDate": 1617914378557,
    "relType": "has",
    "sourceId": "45e054c7a05744f2b3cad2524a1f8c3e",
    "targetId": "c9d142cad5ac4e56b6b43473afbddd65",
    "type": "CreativeWorkhasTypeLabel",
    "visibleToAuthenticatedUsers": false,
    "visibleToPublicUsers": false
  },
  {
    "createdBy": "e1542d3e9a434bcfab474174e92b099f",
    "createdDate": 1617914673375,
    "id": "53588274d2a4445c8b48a99c7a613636",
    "internalTimestamp": "000001617914673375.000084679792543403",
    "lastModifiedDate": 1617914673375,
    "relType": "has",
    "sourceId": "7d2d82110af046f7b2c304423842899e",
    "targetId": "c9d142cad5ac4e56b6b43473afbddd65",
    "type": "CreativeWorkhasTypeLabel",
    "visibleToAuthenticatedUsers": false,
    "visibleToPublicUsers": false
  },
  {
    "createdBy": "e1542d3e9a434bcfab474174e92b099f",
    "createdDate": 1617915640464,
    "id": "2da99a6bdeb448b5b2248b2b95a53296",
    "internalTimestamp": "000001617915640464.000085646916032333",
    "lastModifiedDate": 1617915640464,
    "relType": "has",
    "sourceId": "7dcbf4c4032343139730c1f5db5c195c",
    "targetId": "c9d142cad5ac4e56b6b43473afbddd65",
    "type": "CreativeWorkhasTypeLabel",
    "visibleToAuthenticatedUsers": false,
    "visibleToPublicUsers": false
  },
  {
    "createdBy": "e1542d3e9a434bcfab474174e92b099f",
    "createdDate": 1617917561060,
    "id": "8579fb0a4a8945b09399d6ec05bcd17c",
    "internalTimestamp": "000001617917561060.000087567581521107",
    "lastModifiedDate": 1617917561060,
    "relType": "has",
    "sourceId": "737800c1b7b94cdb90814b44555cf2f4",
    "targetId": "c9d142cad5ac4e56b6b43473afbddd65",
    "type": "CreativeWorkhasTypeLabel",
    "visibleToAuthenticatedUsers": false,
    "visibleToPublicUsers": false
  },
  {
    "createdBy": "e1542d3e9a434bcfab474174e92b099f",
    "createdDate": 1616705732572,
    "id": "92070c3d55da4b5892ea621a4508b330",
    "internalTimestamp": "000001616705732572.000100541350791131",
    "lastModifiedDate": 1616705732572,
    "relType": "has",
    "sourceId": "384fa6f2f2a545d79ab9746b4f24dc0a",
    "targetId": "5b1fefb251584cb1bff1b5fd63b9f227",
    "type": "CreativeWorkhasTypeLabel",
    "visibleToAuthenticatedUsers": false,
    "visibleToPublicUsers": false
  },
  {
    "createdBy": "e1542d3e9a434bcfab474174e92b099f",
    "createdDate": 1616705858088,
    "id": "b1fd1817e0c541f9875815976c3714dc",
    "internalTimestamp": "000001616705858088.000100666869918802",
    "lastModifiedDate": 1616705858088,
    "relType": "has",
    "sourceId": "5bc2af370078482fbc336ac666459bc2",
    "targetId": "5b1fefb251584cb1bff1b5fd63b9f227",
    "type": "CreativeWorkhasTypeLabel",
    "visibleToAuthenticatedUsers": false,
    "visibleToPublicUsers": false
  },
  {
    "createdBy": "e1542d3e9a434bcfab474174e92b099f",
    "createdDate": 1616707354023,
    "id": "23844d140d0846c7b417de3c305d0091",
    "internalTimestamp": "000001616707354023.000102162833191300",
    "lastModifiedDate": 1616707354023,
    "relType": "has",
    "sourceId": "96eafc5ee4f946ada0f159a8aa7a7872",
    "targetId": "5b1fefb251584cb1bff1b5fd63b9f227",
    "type": "CreativeWorkhasTypeLabel",
    "visibleToAuthenticatedUsers": false,
    "visibleToPublicUsers": false
  },
  {
    "createdBy": "e1542d3e9a434bcfab474174e92b099f",
    "createdDate": 1616707418392,
    "id": "d85350fad02347548a2b4bed8454dad1",
    "internalTimestamp": "000001616707418392.000102227203212136",
    "lastModifiedDate": 1616707418392,
    "relType": "has",
    "sourceId": "91d69ebfc06141f6b1c969b982cc43a7",
    "targetId": "5b1fefb251584cb1bff1b5fd63b9f227",
    "type": "CreativeWorkhasTypeLabel",
    "visibleToAuthenticatedUsers": false,
    "visibleToPublicUsers": false
  },
  {
    "createdBy": "e1542d3e9a434bcfab474174e92b099f",
    "createdDate": 1616707505408,
    "id": "764b8b68b4394b54bebfe6429c720abf",
    "internalTimestamp": "000001616707505408.000102314220464173",
    "lastModifiedDate": 1616707505408,
    "relType": "has",
    "sourceId": "db91aa4a9ee7475cb381cdb0781d2820",
    "targetId": "5b1fefb251584cb1bff1b5fd63b9f227",
    "type": "CreativeWorkhasTypeLabel",
    "visibleToAuthenticatedUsers": false,
    "visibleToPublicUsers": false
  },
  {
    "createdBy": "e1542d3e9a434bcfab474174e92b099f",
    "createdDate": 1616969007104,
    "id": "0ee95063adfe4006b051a710ca05c4b2",
    "internalTimestamp": "000001616969007104.000160049518460165",
    "lastModifiedDate": 1616969007104,
    "relType": "has",
    "sourceId": "19645bf194704cc0badca1cb8312d532",
    "targetId": "5b1fefb251584cb1bff1b5fd63b9f227",
    "type": "CreativeWorkhasTypeLabel",
    "visibleToAuthenticatedUsers": false,
    "visibleToPublicUsers": false
  },
  {
    "createdBy": "e1542d3e9a434bcfab474174e92b099f",
    "createdDate": 1616969181088,
    "id": "5ce583c12c7245428e9f998c201a54c9",
    "internalTimestamp": "000001616969181088.000160223614803059",
    "lastModifiedDate": 1616969181088,
    "relType": "has",
    "sourceId": "a69472c795f0431b9d9bb65b682a6011",
    "targetId": "5b1fefb251584cb1bff1b5fd63b9f227",
    "type": "CreativeWorkhasTypeLabel",
    "visibleToAuthenticatedUsers": false,
    "visibleToPublicUsers": false
  },
  {
    "createdBy": "e1542d3e9a434bcfab474174e92b099f",
    "createdDate": 1616968546650,
    "id": "11cebcf4d5a24425838d225a114c518f",
    "internalTimestamp": "000001616968546650.000159589069479810",
    "lastModifiedDate": 1616968546650,
    "relType": "has",
    "sourceId": "62e497490f6b4c3ead94ae0b5dad133c",
    "targetId": "acaff6b7bccd4a0e9a7abe8a4136825a",
    "type": "CreativeWorkhasTypeLabel",
    "visibleToAuthenticatedUsers": false,
    "visibleToPublicUsers": false
  },
  {
    "createdBy": "e1542d3e9a434bcfab474174e92b099f",
    "createdDate": 1616968711333,
    "id": "41c7e2c583dd4f8cbcef138f013acfde",
    "internalTimestamp": "000001616968711333.000159753750650825",
    "lastModifiedDate": 1616968711333,
    "relType": "has",
    "sourceId": "40ea3d8aa1c6462aaea6e2c4ad1edc31",
    "targetId": "acaff6b7bccd4a0e9a7abe8a4136825a",
    "type": "CreativeWorkhasTypeLabel",
    "visibleToAuthenticatedUsers": false,
    "visibleToPublicUsers": false
  },
  {
    "createdBy": "e1542d3e9a434bcfab474174e92b099f",
    "createdDate": 1616019932934,
    "id": "5143575075034a0e852417c2114d6e26",
    "internalTimestamp": "000001616019932935.000006294995696527",
    "lastModifiedDate": 1616019932934,
    "relType": "has",
    "sourceId": "cec269b46d7e4784b0840d979d05f67e",
    "targetId": "46e4cd44476b481e8611bfd427491066",
    "type": "CreativeWorkhasTypeLabel",
    "visibleToAuthenticatedUsers": false,
    "visibleToPublicUsers": false
  },
  {
    "createdBy": "e1542d3e9a434bcfab474174e92b099f",
    "createdDate": 1616021795619,
    "id": "e557632f7587445ea4d5d6de36178ff3",
    "internalTimestamp": "000001616021795619.000008157735897607",
    "lastModifiedDate": 1616021795619,
    "relType": "has",
    "sourceId": "4136c4ecc6a94b89a0b9ae4ae844a419",
    "targetId": "46e4cd44476b481e8611bfd427491066",
    "type": "CreativeWorkhasTypeLabel",
    "visibleToAuthenticatedUsers": false,
    "visibleToPublicUsers": false
  },
  {
    "createdBy": "e1542d3e9a434bcfab474174e92b099f",
    "createdDate": 1616534665200,
    "id": "15ad05ff1db145acab929baaffa564e2",
    "internalTimestamp": "000001616534665200.000004675798076828",
    "lastModifiedDate": 1616534665200,
    "relType": "has",
    "sourceId": "f729f23be05047fdafa5adfe3ffbbeb0",
    "targetId": "04cc54e7ffd0404ab4d8689ae7f7e8f3",
    "type": "CreativeWorkhasTypeLabel",
    "visibleToAuthenticatedUsers": false,
    "visibleToPublicUsers": false
  },
  {
    "createdBy": "e1542d3e9a434bcfab474174e92b099f",
    "createdDate": 1616588762499,
    "id": "7a98e0ee64f0424d8b49f970c2e9f3d6",
    "internalTimestamp": "000001616588762499.000028623632434889",
    "lastModifiedDate": 1616588762499,
    "relType": "has",
    "sourceId": "a0e7bc885d124842815ea30d01345421",
    "targetId": "04cc54e7ffd0404ab4d8689ae7f7e8f3",
    "type": "CreativeWorkhasTypeLabel",
    "visibleToAuthenticatedUsers": false,
    "visibleToPublicUsers": false
  },
  {
    "createdBy": "e1542d3e9a434bcfab474174e92b099f",
    "createdDate": 1616022576550,
    "id": "344615ab364f4cb5a580741e49a7941c",
    "internalTimestamp": "000001616022576550.000008938688566542",
    "lastModifiedDate": 1616022576550,
    "relType": "has",
    "sourceId": "4103ace55794401f9faee9f3c9e1a55f",
    "targetId": "00e6c6dfe1714c7a8e58ac7199c7ba7f",
    "type": "CreativeWorkhasTypeLabel",
    "visibleToAuthenticatedUsers": false,
    "visibleToPublicUsers": false
  },
  {
    "createdBy": "e1542d3e9a434bcfab474174e92b099f",
    "createdDate": 1616705677554,
    "id": "8e65626933a846e3accc31406ffecc3b",
    "internalTimestamp": "000001616705677554.000100486331712528",
    "lastModifiedDate": 1616705677554,
    "relType": "has",
    "sourceId": "9b8a94a1ef9a481fae73728858d48207",
    "targetId": "00e6c6dfe1714c7a8e58ac7199c7ba7f",
    "type": "CreativeWorkhasTypeLabel",
    "visibleToAuthenticatedUsers": false,
    "visibleToPublicUsers": false
  }
]